modelhub/__init__.py
modelhub/_async_client.py
modelhub/_async_mh.py
modelhub/_constants.py
modelhub/_sync_client.py
modelhub/_sync_mh.py
modelhub/modelhub.py
modelhub/types/__init__.py
modelhub/types/_base.py
modelhub/types/_request.py
modelhub/types/_types.py
modelhub/types/audio/__init__.py
modelhub/types/audio/create.py
modelhub/types/audio/transcription.py
modelhub/types/embedding/__init__.py
modelhub/types/embedding/create.py
modelhub/types/embedding/embedding.py
modelhub/types/errors/__init__.py
modelhub/types/errors/_base.py
modelhub/types/errors/errors.py
modelhub/types/errors/message.py
modelhub/types/errors/status_code.py
modelhub/types/generation/__init__.py
modelhub/types/generation/generation.py
modelhub/types/generation/generation_chunk.py
modelhub/types/generation/generation_params.py
modelhub/types/generation/message.py
modelhub/types/generation/message_params.py
modelhub/types/generation/named_tool_choice_param.py
modelhub/types/generation/tokenize.py
modelhub/types/generation/tool_choice_option_param.py
modelhub/types/generation/tool_param.py
modelhub/types/model_info.py
modelhub/types/pricing.py
modelhub/types/rerank/__init__.py
modelhub/types/rerank/create.py
modelhub/types/rerank/rerank.py
modelhub/types/shared_params/function_definition.py
modelhub/types/shared_params/function_parameters.py
modelhub/types/shared_params/response_format.py
modelhub/types/tokenize.py
puyuan_modelhub-3.0.0.dist-info/LICENSE
puyuan_modelhub-3.0.0.dist-info/METADATA
puyuan_modelhub-3.0.0.dist-info/WHEEL
puyuan_modelhub-3.0.0.dist-info/RECORD
